[
  {
    "Model": "STRF Generator",
    "Cost": "-",
    "Edges": "-",
    "Run Time": "-",
    "Replans": "-",
    "Nominal Cost": "-",
    "Deviation Cost": "-"
  },
  {
    "Model": "Discrete Uncertainty",
    "Cost": "99.666",
    "Edges": 198,
    "Run Time": "4.31s",
    "Replans": "-",
    "Nominal Cost": "-",
    "Deviation Cost": "-"
  },
  {
    "Model": "Discrete Uncertainty Adaptive",
    "Cost": "-",
    "Edges": "-",
    "Run Time": "-",
    "Replans": "-",
    "Nominal Cost": "-",
    "Deviation Cost": "-"
  },
  {
    "Model": "Budgeted Uncertainty",
    "Cost": "72.924",
    "Edges": 198,
    "Run Time": "60.05s",
    "Replans": "-",
    "Nominal Cost": "61.332",
    "Deviation Cost": "11.592"
  },
  {
    "Model": "DStar Lite",
    "Cost": "123.482",
    "Edges": 198,
    "Run Time": "1.46s",
    "Replans": 18,
    "Nominal Cost": "-",
    "Deviation Cost": "-"
  },
  {
    "Model": "DStar Lite Discrete Uncertainty",
    "Cost": "108.307",
    "Edges": 198,
    "Run Time": "1.44s",
    "Replans": 18,
    "Nominal Cost": "-",
    "Deviation Cost": "-"
  },
  {
    "Model": "DStar Lite Discrete Uncertainty Adaptive",
    "Cost": "-",
    "Edges": "-",
    "Run Time": "-",
    "Replans": "-",
    "Nominal Cost": "-",
    "Deviation Cost": "-"
  },
  {
    "Model": "DStar Lite Budgeted Uncertainty",
    "Cost": "113.647",
    "Edges": 198,
    "Run Time": "1.45s",
    "Replans": 18,
    "Nominal Cost": "-",
    "Deviation Cost": "-"
  }
]